sockeye_serving/__init__.py
sockeye_serving/default_handler.py
sockeye_serving/ko_handler.py
sockeye_serving/sockeye_handler.py
sockeye_serving/text_processor.py
sockeye_serving/utils.py
sockeye_serving/zh_handler.py
sockeye_serving/scripts/COPYING
sockeye_serving/scripts/detokenize.pl
sockeye_serving/scripts/normalize-punctuation.perl
sockeye_serving/scripts/normalize.pl
sockeye_serving/scripts/remove-non-printing-char.perl
sockeye_serving/scripts/tokenizer.perl
sockeye_serving/scripts/nonbreaking_prefixes/README.txt
sockeye_serving/scripts/nonbreaking_prefixes/nonbreaking_prefix.ca
sockeye_serving/scripts/nonbreaking_prefixes/nonbreaking_prefix.cs
sockeye_serving/scripts/nonbreaking_prefixes/nonbreaking_prefix.de
sockeye_serving/scripts/nonbreaking_prefixes/nonbreaking_prefix.el
sockeye_serving/scripts/nonbreaking_prefixes/nonbreaking_prefix.en
sockeye_serving/scripts/nonbreaking_prefixes/nonbreaking_prefix.es
sockeye_serving/scripts/nonbreaking_prefixes/nonbreaking_prefix.fi
sockeye_serving/scripts/nonbreaking_prefixes/nonbreaking_prefix.fr
sockeye_serving/scripts/nonbreaking_prefixes/nonbreaking_prefix.ga
sockeye_serving/scripts/nonbreaking_prefixes/nonbreaking_prefix.hu
sockeye_serving/scripts/nonbreaking_prefixes/nonbreaking_prefix.is
sockeye_serving/scripts/nonbreaking_prefixes/nonbreaking_prefix.it
sockeye_serving/scripts/nonbreaking_prefixes/nonbreaking_prefix.lt
sockeye_serving/scripts/nonbreaking_prefixes/nonbreaking_prefix.lv
sockeye_serving/scripts/nonbreaking_prefixes/nonbreaking_prefix.nl
sockeye_serving/scripts/nonbreaking_prefixes/nonbreaking_prefix.pl
sockeye_serving/scripts/nonbreaking_prefixes/nonbreaking_prefix.pt
sockeye_serving/scripts/nonbreaking_prefixes/nonbreaking_prefix.ro
sockeye_serving/scripts/nonbreaking_prefixes/nonbreaking_prefix.ru
sockeye_serving/scripts/nonbreaking_prefixes/nonbreaking_prefix.sk
sockeye_serving/scripts/nonbreaking_prefixes/nonbreaking_prefix.sl
sockeye_serving/scripts/nonbreaking_prefixes/nonbreaking_prefix.sv
sockeye_serving-2.1.0.dist-info/LICENSE
sockeye_serving-2.1.0.dist-info/METADATA
sockeye_serving-2.1.0.dist-info/NOTICE
sockeye_serving-2.1.0.dist-info/WHEEL
sockeye_serving-2.1.0.dist-info/top_level.txt
sockeye_serving-2.1.0.dist-info/RECORD
