Metadata-Version: 2.1
Name: sockeye-serving
Version: 2.1.0
Summary: A containerized service for neural machine translation
Home-page: https://github.com/jamesewoo/sockeye-serving
Author: James Woo
Author-email: james.e.woo@gmail.com
License: UNKNOWN
Platform: UNKNOWN
Classifier: Programming Language :: Python :: 3.6
Classifier: Programming Language :: Perl
Classifier: Programming Language :: Unix Shell
Classifier: License :: OSI Approved :: Apache Software License
Classifier: Operating System :: MacOS :: MacOS X
Classifier: Operating System :: Unix
Classifier: Development Status :: 5 - Production/Stable
Classifier: Topic :: Internet :: WWW/HTTP :: HTTP Servers
Classifier: Topic :: Scientific/Engineering :: Artificial Intelligence
Requires-Dist: model-archiver
Requires-Dist: pyyaml
Requires-Dist: requests
